morph/__init__.py
morph/api/__init__.py
morph/api/app.py
morph/api/auth.py
morph/api/cloud/__init__.py
morph/api/cloud/base.py
morph/api/cloud/client.py
morph/api/cloud/types.py
morph/api/context.py
morph/api/custom_types.py
morph/api/error.py
morph/api/handler.py
morph/api/plugin.py
morph/api/service.py
morph/api/templates/index.html
morph/api/utils.py
morph/cli/README.md
morph/cli/__init__.py
morph/cli/flags.py
morph/cli/main.py
morph/cli/params.py
morph/cli/requires.py
morph/cli/types.py
morph/config/__init__.py
morph/config/project.py
morph/constants.py
morph/include/__init__.py
morph/include/starter_template/.env
morph/include/starter_template/.gitignore
morph/include/starter_template/.mock_user_context.json
morph/include/starter_template/README.md
morph/include/starter_template/components.json
morph/include/starter_template/morph_project.yml
morph/include/starter_template/package.json
morph/include/starter_template/src/__init__.py
morph/include/starter_template/src/pages/404.tsx
morph/include/starter_template/src/pages/_app.tsx
morph/include/starter_template/src/pages/_components/header.tsx
morph/include/starter_template/src/pages/_components/table-of-contents.tsx
morph/include/starter_template/src/pages/_lib/utils.ts
morph/include/starter_template/src/pages/index.css
morph/include/starter_template/src/pages/index.mdx
morph/include/starter_template/static/favicon.ico
morph/include/starter_template/tsconfig.json
morph/include/starter_template/vite.config.ts
morph/py.typed
morph/task/__init__.py
morph/task/api.py
morph/task/base.py
morph/task/clean.py
morph/task/compile.py
morph/task/config.py
morph/task/context.py
morph/task/deploy.py
morph/task/init.py
morph/task/new.py
morph/task/plugin.py
morph/task/resource.py
morph/task/run.py
morph/task/server.py
morph/task/utils/__init__.py
morph/task/utils/connection.py
morph/task/utils/connections/athena/api.py
morph/task/utils/connections/athena/usecase.py
morph/task/utils/connections/bigquery/api.py
morph_data-0.3.1.dist-info/METADATA
morph_data-0.3.1.dist-info/WHEEL
morph_data-0.3.1.dist-info/entry_points.txt
morph_data-0.3.1.dist-info/RECORD
