Metadata-Version: 2.1
Name: morph-data
Version: 0.3.1
Summary: Morph is a python-centric full-stack framework for building and deploying data apps.
Home-page: https://www.morph-data.io
License: Apache-2.0
Author: Morph
Author-email: contact@morphdb.io
Requires-Python: >=3.9.2,<3.13
Classifier: Development Status :: 5 - Production/Stable
Classifier: Environment :: Console
Classifier: Environment :: Web Environment
Classifier: Intended Audience :: Developers
Classifier: Intended Audience :: Science/Research
Classifier: License :: OSI Approved :: Apache Software License
Classifier: Programming Language :: Python :: 3
Classifier: Programming Language :: Python :: 3.10
Classifier: Programming Language :: Python :: 3.11
Classifier: Programming Language :: Python :: 3.12
Classifier: Programming Language :: Python :: 3.13
Classifier: Programming Language :: Python :: 3.9
Classifier: Topic :: Database :: Front-Ends
Classifier: Topic :: Office/Business :: Financial :: Spreadsheet
Classifier: Topic :: Scientific/Engineering :: Information Analysis
Classifier: Topic :: Scientific/Engineering :: Visualization
Classifier: Topic :: Software Development :: Libraries :: Application Frameworks
Classifier: Topic :: Software Development :: Widget Sets
Requires-Dist: Jinja2 (>=3.1.6,<4.0.0)
Requires-Dist: aiomysql (>=0.2.0,<0.3.0)
Requires-Dist: boto3 (>=1.26.80,<2.0.0)
Requires-Dist: click (>=8.1.7,<9.0.0)
Requires-Dist: colorama (>=0.4.6,<0.5.0)
Requires-Dist: colorlog (>=6.8.2,<7.0.0)
Requires-Dist: cryptography (>=44.0.1,<45.0.0)
Requires-Dist: duckdb (>=1.0.0,<2.0.0)
Requires-Dist: fastapi (>=0.115.4,<0.116.0)
Requires-Dist: fastapi-inertia (>=1.0.3,<2.0.0)
Requires-Dist: google (>=3.0.0,<4.0.0)
Requires-Dist: google-api-python-client (>=2.139.0,<3.0.0)
Requires-Dist: google-cloud-bigquery (>=3.25.0,<4.0.0)
Requires-Dist: gspread (>=6.1.2,<7.0.0)
Requires-Dist: httpx (>=0.27.0,<0.28.0)
Requires-Dist: itsdangerous (>=2.2.0,<3.0.0)
Requires-Dist: pandas (>=2.1.3,<3.0.0)
Requires-Dist: paramiko (>=3.4.0,<4.0.0)
Requires-Dist: psycopg2-binary (>=2.9.9,<3.0.0)
Requires-Dist: pyarrow (>=17.0.0,<18.0.0)
Requires-Dist: pydantic (>=2.5.3,<3.0.0)
Requires-Dist: python-dotenv (>=1.0.1,<2.0.0)
Requires-Dist: python-multipart (>=0.0.18,<0.0.19)
Requires-Dist: pyyaml (>=6.0.1,<7.0.0)
Requires-Dist: requests (>=2.31.0,<3.0.0)
Requires-Dist: snowflake-connector-python (>=3.11.0,<4.0.0)
Requires-Dist: sqlalchemy (>=2.0.36,<3.0.0)
Requires-Dist: sqlalchemy-pytds (>=1.0.2,<2.0.0)
Requires-Dist: sqlglot (>=25.22.0,<26.0.0)
Requires-Dist: sshtunnel (>=0.4.0,<0.5.0)
Requires-Dist: starlette (>=0.41.3,<0.42.0)
Requires-Dist: tabulate (>=0.9.0,<0.10.0)
Requires-Dist: tqdm (>=4.7.4,<5.0.0)
Requires-Dist: typing-extensions (>=4.12.2,<5.0.0)
Requires-Dist: uvicorn (>=0.32.0,<0.33.0)
Project-URL: Repository, https://github.com/morph-data/morph
